demo_python_project/__init__.py
demo_python_project/asgi.py
demo_python_project/settings.py
demo_python_project/urls.py
demo_python_project/wsgi.py
pyDemo_app/__init__.py
pyDemo_app/admin.py
pyDemo_app/apps.py
pyDemo_app/models.py
pyDemo_app/tests.py
pyDemo_app/views.py
pyDemo_app/migrations/__init__.py
pyDemo_app/migrations/__pycache__/__init__.cpython-310.pyc
pyDemo_app/static/image.png
pyDemo_app/static/css/custom_admin.css
pyDemo_app/static/css/login.css
pyDemo_app/templates/admin/base_site.html
pyDemo_app/templates/admin/login.html
custom_django_style_template-1.0.0.dist-info/METADATA
custom_django_style_template-1.0.0.dist-info/WHEEL
custom_django_style_template-1.0.0.dist-info/top_level.txt
custom_django_style_template-1.0.0.dist-info/RECORD
