Metadata-Version: 2.1
Name: custom-django-style-template
Version: 1.0.0
Summary: A Custom Django admin template with CSS styling.
Home-page: https://github.com/abhishek-cubexo1223/custom_django_style_template.git
Author: Abhishek Yadav
Author-email: abhishek.yadav@cubexo.io
License: UNKNOWN
Platform: UNKNOWN
Classifier: Framework :: Django
Classifier: Programming Language :: Python :: 3
Classifier: License :: OSI Approved :: MIT License
Classifier: Operating System :: OS Independent
Requires-Python: >=3.6
Requires-Dist: django (>=3.2)
